example/__init__.py
example/logger_instance.py
example/playground.py
example/cool/__init__.py
example/cool/fib.py
example/cool/cooler/__init__.py
example/cool/cooler/sleep.py
tdlogging/__init__.py
tdlogging/tdlogger.py
tdlogging/tdprinter.py
tdlogging/tdreader.py
tdlogging-0.0.6.dist-info/LICENSE.txt
tdlogging-0.0.6.dist-info/METADATA
tdlogging-0.0.6.dist-info/WHEEL
tdlogging-0.0.6.dist-info/top_level.txt
tdlogging-0.0.6.dist-info/RECORD
