Metadata-Version: 2.1
Name: tdlogging
Version: 0.0.6
Summary: Classed based logger for Python
Home-page: https://github.com/troppydash/tdlogging
Author: Terry Qi
Author-email: troppydash.developer@gmail.com
License: MIT
Download-URL: https://pypi.org/project/tdlogging/
Keywords: Logger,Class
Platform: UNKNOWN
